ccsf/__init__.py
ccsf/ccsf.py
ccsf/class_discriminative_opt/__init__.py
ccsf/class_discriminative_opt/class_discriminative_opt.py
ccsf/group_centroid_opt/__init__.py
ccsf/group_centroid_opt/group_centroid_opt.py
ccsf-1.0.8.dist-info/LICENSE
ccsf-1.0.8.dist-info/METADATA
ccsf-1.0.8.dist-info/WHEEL
ccsf-1.0.8.dist-info/top_level.txt
ccsf-1.0.8.dist-info/RECORD
