Metadata-Version: 2.1
Name: ccsf
Version: 1.0.8
Summary: Leveraging cell-cell similarity from gene expression data for high-performance spatial and temporal cellular mappings.
Home-page: https://github.com/xinglab-ai/ccsf
Author: Md Tauhidul Islam
Author-email: tauhid@stanford.edu
Classifier: Programming Language :: Python :: 3
Classifier: Operating System :: OS Independent
Requires-Python: >=3.8
License-File: LICENSE
Requires-Dist: leidenalg
Requires-Dist: novosparc
Requires-Dist: numpy
Requires-Dist: pandas
Requires-Dist: phate
Requires-Dist: umap-learn
Requires-Dist: scanpy
Requires-Dist: scikit-learn-extra
Requires-Dist: scipy
